{
  "left" : [ {
    "accessControl" : [ "App Admin" ],
    "outline" : false,
    "label" : "MENU",
    "element" : "menuItem"
  }, {
    "pathsInvolved" : [ "/applicationuser/applicationuserlist" ],
    "accessControl" : [ "App Admin" ],
    "onClick" : "navigate_to_page",
    "outline" : false,
    "label" : "APPLICATION_USER",
    "page" : {
      "sid" : "c97da707-31c8-40ba-9021-e9d13a74cd5b",
      "name" : "Application Users",
      "url" : "/applicationuser/applicationuserlist"
    },
    "element" : "menuItem"
  } ],
  "topBarLeft" : [ ],
  "topBarMiddle" : [ ],
  "topBarRight" : [ {
    "languages" : [ {
      "code" : "en",
      "name" : "English"
    } ],
    "element" : "language"
  } ],
  "right" : [ ]
}